diffmoments/__init__.py
diffmoments/drjit/__init__.py
diffmoments/drjit/bounds.py
diffmoments/extension.py
diffmoments/np/__init__.py
diffmoments/np/bounds.py
diffmoments/torch/__init__.py
diffmoments/torch/ad/__init__.py
diffmoments/torch/ad/bounds.py
diffmoments/torch/bounds.py
diffmoments/torch/moment_problem.py
diffmoments/torch/polynomial.py
diffmoments_ext.cp310-win_amd64.pyd
diffmoments-0.1.0.dist-info/METADATA
diffmoments-0.1.0.dist-info/WHEEL
diffmoments-0.1.0.dist-info/licenses/LICENSE
diffmoments-0.1.0.dist-info/RECORD
