Metadata-Version: 2.1
Name: diffmoments
Version: 0.1.0
Summary: Differentiable moment bounds.
Author-Email: Markus Worchel <m.worchel@tu-berlin.de>
License: BSD 3-Clause License
Project-URL: Homepage, https://github.com/mworchel/differentiable-moment-bounds
Requires-Python: >=3.8
Provides-Extra: test
Requires-Dist: numpy; extra == "test"
Requires-Dist: pytest; extra == "test"
